aa/__init__.py
aa/__main__.py
aa/cli.py
aa/commands/__init__.py
aa/commands/cache_info.py
aa/commands/init.py
aa/commands/list_tasks.py
aa/commands/scan.py
aa/commands/test_id.py
aa/commands/update.py
aa/commands/validate.py
aa/core/__init__.py
aa/core/asana_client.py
aa/core/id_manager.py
aa/core/task_processor.py
aa/models/__init__.py
aa/models/cache.py
aa/models/config.py
aa/models/task.py
aa/utils/__init__.py
aa/utils/cache_manager.py
aa/utils/config_loader.py
aa_cli-0.3.0.dist-info/METADATA
aa_cli-0.3.0.dist-info/WHEEL
aa_cli-0.3.0.dist-info/entry_points.txt
aa_cli-0.3.0.dist-info/RECORD
