Metadata-Version: 2.4
Name: aa-cli
Version: 0.3.0
Summary: Automatic human-readable ID assignment for Asana tasks
Project-URL: Homepage, https://github.com/umaxfun/asana-tools
Project-URL: Repository, https://github.com/umaxfun/asana-tools
Project-URL: Issues, https://github.com/umaxfun/asana-tools/issues
Author-email: umaxfun <umaxfun@users.noreply.github.com>
License: MIT
Keywords: asana,automation,cli,task-management
Classifier: Development Status :: 4 - Beta
Classifier: Intended Audience :: Developers
Classifier: License :: OSI Approved :: MIT License
Classifier: Programming Language :: Python :: 3
Classifier: Programming Language :: Python :: 3.12
Classifier: Topic :: Software Development :: Libraries :: Python Modules
Requires-Python: >=3.12
Requires-Dist: click>=8.1.0
Requires-Dist: httpx>=0.27.0
Requires-Dist: pydantic>=2.0.0
Requires-Dist: pyyaml>=6.0.0
